auger/api/__init__.py
auger/api/auth.py
auger/api/credentials.py
auger/api/dataset.py
auger/api/experiment.py
auger/api/model.py
auger/api/project.py
auger/api/cloud/__init__.py
auger/api/cloud/actual.py
auger/api/cloud/auth.py
auger/api/cloud/base.py
auger/api/cloud/cluster.py
auger/api/cloud/cluster_task.py
auger/api/cloud/data_set.py
auger/api/cloud/experiment.py
auger/api/cloud/experiment_session.py
auger/api/cloud/org.py
auger/api/cloud/pipeline.py
auger/api/cloud/pipeline_file.py
auger/api/cloud/prediction.py
auger/api/cloud/project.py
auger/api/cloud/project_file.py
auger/api/cloud/rest_api.py
auger/api/cloud/trial.py
auger/api/cloud/utils/__init__.py
auger/api/cloud/utils/dataframe.py
auger/api/cloud/utils/exception.py
auger/api/cloud/utils/singleton.py
auger/api/mparts/__init__.py
auger/api/mparts/actual.py
auger/api/mparts/deploy.py
auger/api/mparts/predict.py
auger/api/utils/config.py
auger/api/utils/config_yaml.py
auger/api/utils/context.py
auger/api/utils/fsclient.py
auger/api/utils/json_utils.py
auger/api/utils/local_fsclient.py
auger/api/utils/s3_fsclient.py
auger/cli/__init__.py
auger/cli/cli.py
auger/cli/commands/__init__.py
auger/cli/commands/cmd_auth.py
auger/cli/commands/cmd_dataset.py
auger/cli/commands/cmd_experiment.py
auger/cli/commands/cmd_model.py
auger/cli/commands/cmd_new.py
auger/cli/commands/cmd_project.py
auger/cli/commands/impl/authcmd.py
auger/cli/commands/impl/datasetcmd.py
auger/cli/commands/impl/experimentcmd.py
auger/cli/commands/impl/modelcmd.py
auger/cli/commands/impl/newcmd.py
auger/cli/commands/impl/projectcmd.py
auger/cli/template/auger.yaml
auger/cli/utils/__init__.py
auger/cli/utils/config.py
auger/cli/utils/context.py
auger/cli/utils/decorators.py
auger/cli/utils/formatter.py
auger/cli/utils/template.py
auger.ai-0.2.5.dist-info/LICENSE
auger.ai-0.2.5.dist-info/METADATA
auger.ai-0.2.5.dist-info/WHEEL
auger.ai-0.2.5.dist-info/entry_points.txt
auger.ai-0.2.5.dist-info/top_level.txt
auger.ai-0.2.5.dist-info/RECORD
