Metadata-Version: 2.1
Name: auger.ai
Version: 0.2.5
Summary: Auger python and command line interface package
Home-page: https://github.com/deeplearninc/auger-ai
Author: Deep Learn, Inc.
Author-email: augerai@dplrn.com
License: MIT
Keywords: augerai auger ai machine learning automl deeplearn api sdk
Platform: any
Classifier: Development Status :: 3 - Alpha
Classifier: Intended Audience :: Developers
Classifier: Intended Audience :: System Administrators
Classifier: Topic :: Software Development :: Build Tools
Classifier: License :: OSI Approved :: MIT License
Classifier: Programming Language :: Python :: 3
Classifier: Programming Language :: Python :: 3.6
Classifier: Programming Language :: Python :: 3.7
Classifier: Programming Language :: Python :: 3 :: Only
Requires-Python: >=3
Requires-Dist: click
Requires-Dist: requests
Requires-Dist: shortuuid
Requires-Dist: auger-hub-api-client (==0.6.8)
Requires-Dist: ruamel.yaml
Requires-Dist: pandas (>=0.23.4)
Requires-Dist: setuptools (>=40.1.0)
Requires-Dist: s3fs
Requires-Dist: boto3
Requires-Dist: smart-open (==1.9.0)
Provides-Extra: all
Requires-Dist: pytest ; extra == 'all'
Requires-Dist: pytest-cov ; extra == 'all'
Requires-Dist: pytest-xdist ; extra == 'all'
Requires-Dist: flake8 ; extra == 'all'
Requires-Dist: mock ; extra == 'all'
Provides-Extra: testing
Requires-Dist: pytest ; extra == 'testing'
Requires-Dist: pytest-cov ; extra == 'testing'
Requires-Dist: pytest-xdist ; extra == 'testing'
Requires-Dist: flake8 ; extra == 'testing'
Requires-Dist: mock ; extra == 'testing'
